{
    "L'AMISTAT": "#FF0000",
    "EL GRAU": "#00FF00",
    "RAFALELL-VISTABELLA": "#0000FF",
    "LA CARRASCA": "#FFFF00",
    "BENIFERRI": "#FF00FF",
    "EL SALER": "#00FFFF",
    "CARPESA": "#FFA500",
    "SANT ANTONI": "#8A2BE2",
    "MARXALENES": "#800000",
    "EL CALVARI": "#808000",
    "LES TENDETES": "#00CED1",
    "EXPOSICIO": "#9400D3",
    "LA VEGA BAIXA": "#DC143C",
    "EL PILAR": "#FFD700",
    "CAMI FONDO": "#556B2F",
    "RUSSAFA": "#FF69B4",
    "SAFRANAR": "#008080",
    "EN CORTS": "#2E8B57",
    "LES CASES DE BARCENA": "#FF6347",
    "MAHUELLA-TAULADELLA": "#000080",
    "MASSARROJOS": "#F08080",
    "SANT PAU": "#4B0082",
    "JAUME ROIG": "#FFFFE0",
    "SANT MARCEL.LI": "#9ACD32",
    "LA CREU COBERTA": "#00FA9A",
    "CAMI REAL": "#8B008B",
    "LA PUNTA": "#9932CC",
    "BENIMAMET": "#EEE8AA",
    "SANT LLORENS": "#B8860B",
    "CIUTAT FALLERA": "#556B2F",
    "NOU MOLES": "#FF7F50",
    "LA LLUM": "#FF4500",
    "LA MALVA-ROSA": "#DA70D6",
    "MORVEDRE": "#8B4513",
    "CAMPANAR": "#A0522D",
    "EL CARME": "#FF8C00",
    "CIUTAT UNIVERSITARIA": "#FFA07A",
    "BETERO": "#FFDAB9",
    "MESTALLA": "#CD853F",
    "LA XEREA": "#FF00FF",
    "ALBORS": "#7B68EE",
    "ARRANCAPINS": "#4169E1",
    "LA ROQUETA": "#C71585",
    "LA GRAN VIA": "#00FF7F",
    "LA CREU DEL GRAU": "#D2691E",
    "SANT ISIDRE": "#8B0000",
    "MALILLA": "#6495ED",
    "BENICALAP": "#DDA0DD",
    "LA PETXINA": "#B0E0E6",
    "PENYA-ROJA": "#800080",
    "FAITANAR": "#FF69B4",
    "PINEDO": "#DDA0DD",
    "CASTELLAR-L'OLIVERAL": "#6495ED",
    "EL FORN D'ALCEDO": "#B0E0E6",
    "AIORA": "#800080",
    "NA ROVELLA": "#FF69B4",
    "FAVARA": "#DDA0DD",
    "L'HORT DE SENABRE": "#6495ED",
    "NATZARET": "#B0E0E6",
    "LA FONTETA S.LLUIS": "#800080",
    "CIUTAT JARDI": "#FF69B4",
    "CAMI DE VERA": "#DDA0DD",
    "EL PALMAR": "#6495ED",
    "EL PERELLONET": "#B0E0E6",
    "VARA DE QUART": "#800080",
    "SOTERNES": "#FF69B4",
    "LA FONTSANTA": "#DDA0DD",
    "EL BOTANIC": "#6495ED",
    "BORBOTO": "#B0E0E6",
    "BENIFARAIG": "#800080",
    "TORREFIEL": "#FF69B4",
    "TORMOS": "#DDA0DD",
    "BENIMACLET": "#6495ED",
    "TRINITAT": "#B0E0E6",
    "CABANYAL-CANYAMELAR": "#800080",
    "EL MERCAT": "#FF69B4",
    "EL PLA DEL REMEI": "#DDA0DD",
    "L'ILLA PERDUDA": "#6495ED",
    "TRES FORQUES": "#B0E0E6",
    "PATRAIX": "#800080",
    "LA RAIOSA": "#FF69B4",
    "POBLE NOU": "#DDA0DD",
    "CIUTAT DE LES ARTS I DE LES CIENCIES": "#6495ED",
    "LA TORRE": "#B0E0E6",
    "SANT FRANCESC": "#800080",
    "ELS ORRIOLS": "#FF69B4",
    "LA SEU": "#DDA0DD",
    "MONTOLIVET": "#6495ED"
}